{
  "tags": [
    { "name": "2S" },
    { "name": "3S" },
    { "name": "Boss" },
    { "name": "Con Dâu Nuôi từ Bé" },
    { "name": "Công Sở" },
    { "name": "Dân Quốc" },
    { "name": "Dị Nhân" },
    { "name": "Gương Vỡ Lại Lành" },
    { "name": "Hiện Thực" },
    { "name": "Học Đường" },
    { "name": "Kinh Dị" },
    { "name": "Linh Dị" },
    { "name": "Marvel" },
    { "name": "Mỹ Thực" },
    { "name": "Nhân Viên" },
    { "name": "Nữ Truy" },
    { "name": "Phim" },
    { "name": "Quân Nhân" },
    { "name": "Review Phim" },
    { "name": "Review Truyện" },
    { "name": "S2" },
    { "name": "Showbiz" },
    { "name": "Siêu Anh Hùng" },
    { "name": "Sạch" },
    { "name": "Sủng" },
    { "name": "Thanh Mai Trúc Mã" },
    { "name": "Thanh Xuân Vườn Trường" },
    { "name": "Thầm Mến" },
    { "name": "Thực Tế" },
    { "name": "Trinh Thám" },
    { "name": "Tổng Tài" },
    { "name": "Yêu Thầm" }
  ]
}
